djseong/__init__.py
djseong/namespace_a/__init__.py
djseong/namespace_a/module_a.py
djseong/namespace_foo_b/__init__.py
djseong/namespace_foo_b/module_b.py
djseong_test_foo_2-0.1.2.dist-info/METADATA
djseong_test_foo_2-0.1.2.dist-info/WHEEL
djseong_test_foo_2-0.1.2.dist-info/top_level.txt
djseong_test_foo_2-0.1.2.dist-info/RECORD
